mustaching/__init__.py
mustaching/main.py
mustaching-4.0.4.dist-info/METADATA
mustaching-4.0.4.dist-info/WHEEL
mustaching-4.0.4.dist-info/licenses/LICENSE.txt
mustaching-4.0.4.dist-info/RECORD
